dharitri_sdk_wallet/__init__.py
dharitri_sdk_wallet/constants.py
dharitri_sdk_wallet/core.py
dharitri_sdk_wallet/errors.py
dharitri_sdk_wallet/interfaces.py
dharitri_sdk_wallet/mnemonic.py
dharitri_sdk_wallet/mnemonic_test.py
dharitri_sdk_wallet/pem_entry.py
dharitri_sdk_wallet/pem_entry_test.py
dharitri_sdk_wallet/py.typed
dharitri_sdk_wallet/user_keys.py
dharitri_sdk_wallet/user_pem.py
dharitri_sdk_wallet/user_signer.py
dharitri_sdk_wallet/user_test.py
dharitri_sdk_wallet/user_verifer.py
dharitri_sdk_wallet/user_wallet.py
dharitri_sdk_wallet/validator_keys.py
dharitri_sdk_wallet/validator_pem.py
dharitri_sdk_wallet/validator_signer.py
dharitri_sdk_wallet/validator_test.py
dharitri_sdk_wallet/validator_verifier.py
dharitri_sdk_wallet/crypto/__init__.py
dharitri_sdk_wallet/crypto/constants.py
dharitri_sdk_wallet/crypto/decryptor.py
dharitri_sdk_wallet/crypto/encrypted_data.py
dharitri_sdk_wallet/crypto/encryptor.py
dharitri_sdk_wallet/crypto/randomness.py
dharitri_sdk_wallet/libraries/__init__.py
dharitri_sdk_wallet/libraries/bls_facade.py
dharitri_sdk_wallet/libraries/bls_facade_test.py
dharitri_sdk_wallet/libraries/libbls.dll
dharitri_sdk_wallet/libraries/libbls.dylib
dharitri_sdk_wallet/libraries/libbls.so
dharitri_sdk_wallet/libraries/libbls_arm64.dylib
dharitri_sdk_wallet-0.0.2.dist-info/METADATA
dharitri_sdk_wallet-0.0.2.dist-info/WHEEL
dharitri_sdk_wallet-0.0.2.dist-info/licenses/LICENSE
dharitri_sdk_wallet-0.0.2.dist-info/RECORD
