Metadata-Version: 2.3
Name: dharitri-sdk-wallet
Version: 0.0.2
Summary: Wallet & crypto components of Dharitri Python SDK.
Project-URL: Homepage, https://github.com/Dharitri-org/drt-sdk-py-wallet
Author: Dharitri
License-Expression: MIT
License-File: LICENSE
Classifier: License :: OSI Approved :: MIT License
Classifier: Operating System :: OS Independent
Classifier: Programming Language :: Python :: 3
Requires-Python: >=3.8
Requires-Dist: cryptography==36.0.2
Requires-Dist: dharitri-sdk-core>=0.0.2
Requires-Dist: mnemonic==0.20
Requires-Dist: pynacl==1.5.0
